codemaoLang/__init__.py
codemaoLang-1.1.0.dist-info/LICENSE
codemaoLang-1.1.0.dist-info/METADATA
codemaoLang-1.1.0.dist-info/WHEEL
codemaoLang-1.1.0.dist-info/top_level.txt
codemaoLang-1.1.0.dist-info/RECORD
