Metadata-Version: 2.1
Name: codemaoLang
Version: 1.1.0
Summary: 一个为编程猫api打造的高度包装的Python库
Home-page: https://github.com/MinesomeBTQ/CodemaoLang
Author: BT.Q
Author-email: BT.Q@qq.com
License: UNKNOWN
Platform: UNKNOWN
Classifier: Programming Language :: Python :: 3
Classifier: License :: OSI Approved :: MIT License
Classifier: Operating System :: OS Independent
License-File: LICENSE
Requires-Dist: requests
